meteor/__init__.py
meteor/_version.py
meteor/diffmaps.py
meteor/iterative.py
meteor/metadata.py
meteor/mtzio.py
meteor/rsmap.py
meteor/scale.py
meteor/settings.py
meteor/sfcalc.py
meteor/testing.py
meteor/tv.py
meteor/utils.py
meteor/validate.py
meteor/scripts/__init__.py
meteor/scripts/common.py
meteor/scripts/diffmap.py
meteor/scripts/phaseboost.py
meteor_maps-0.4.0.dist-info/licenses/LICENSE
meteor_maps-0.4.0.dist-info/METADATA
meteor_maps-0.4.0.dist-info/WHEEL
meteor_maps-0.4.0.dist-info/entry_points.txt
meteor_maps-0.4.0.dist-info/top_level.txt
meteor_maps-0.4.0.dist-info/RECORD
