Metadata-Version: 2.4
Name: meteor-maps
Version: 0.4.0
Summary: denoise crystallographic difference maps
Author-email: Alisia Fadini <af840@cam.ac.uk>, Thomas Lane <thomas.joseph.lane@gmail.com>
Project-URL: Homepage, https://github.com/rs-station/meteor
Project-URL: Issues, https://github.com/rs-station/meteor/issues
Classifier: Programming Language :: Python :: 3
Classifier: License :: OSI Approved :: MIT License
Classifier: Operating System :: OS Independent
Requires-Python: >=3.11
License-File: LICENSE
Requires-Dist: numpy>=1.26
Requires-Dist: scipy>=1.14.0
Requires-Dist: gemmi>=0.7.0
Requires-Dist: scikit-image>=0.24.0
Requires-Dist: reciprocalspaceship>=1.0.2
Requires-Dist: structlog>=24.4.0
Requires-Dist: pydantic>=2.10.0
Requires-Dist: setuptools>=75.5.0
Provides-Extra: tests
Requires-Dist: pytest; extra == "tests"
Requires-Dist: pytest-cov; extra == "tests"
Requires-Dist: pytest-xdist; extra == "tests"
Requires-Dist: nbmake; extra == "tests"
Provides-Extra: notebooks
Requires-Dist: matplotlib; extra == "notebooks"
Dynamic: license-file
